lumigator_schemas/__init__.py
lumigator_schemas/completions.py
lumigator_schemas/datasets.py
lumigator_schemas/experiments.py
lumigator_schemas/extras.py
lumigator_schemas/jobs.py
lumigator_schemas/models.py
lumigator_schemas-0.0.2.dist-info/METADATA
lumigator_schemas-0.0.2.dist-info/WHEEL
lumigator_schemas-0.0.2.dist-info/RECORD
