Metadata-Version: 2.4
Name: lumigator-schemas
Version: 0.0.2
Summary: Schemas used for REST API communication
Requires-Python: >=3.11
Requires-Dist: pydantic>=2.8.0
